tenadggbot/__init__.py
tenadggbot/bot.py
tenadggbot/chat.py
tenadggbot/errors.py
tenadggbot/event.py
tenadggbot/message.py
tenadggbot/user.py
tena_dgg_bot-0.3.1.dist-info/LICENSE
tena_dgg_bot-0.3.1.dist-info/METADATA
tena_dgg_bot-0.3.1.dist-info/WHEEL
tena_dgg_bot-0.3.1.dist-info/top_level.txt
tena_dgg_bot-0.3.1.dist-info/RECORD
