Metadata-Version: 2.1
Name: tena-dgg-bot
Version: 0.3.1
Summary: A library for making a bot in Destiny.gg chat. Fork of https://github.com/Fritz-02/dgg-bot
Home-page: https://github.com/tenacious210/tena-dgg-bot/
Author: tena
Project-URL: Bug Tracker, https://github.com/tenacious210/tena-dgg-bot/issues
Classifier: Development Status :: 4 - Beta
Classifier: License :: OSI Approved :: MIT License
Classifier: Operating System :: OS Independent
Classifier: Programming Language :: Python :: 3.8
Classifier: Programming Language :: Python :: 3.9
Classifier: Programming Language :: Python :: 3.10
Classifier: Topic :: Communications :: Chat
Requires-Python: >=3.8
License-File: LICENSE
